hdf/__init__.py
hdf/config.py
hdf-2023.12.4.dist-info/LICENSE
hdf-2023.12.4.dist-info/METADATA
hdf-2023.12.4.dist-info/WHEEL
hdf-2023.12.4.dist-info/RECORD
